Metadata-Version: 1.1
Name: tictactoelib
Version: 0.2.4
Summary: Ultimate Tic Tac Toe game logic (Lua and Python bindings)
Home-page: http://github.com/Motiejus/ultimate-tic-tac-toe
Author: Motiejus Jakštys
Author-email: desired.mta@gmail.com
License: Apache2
Platform: UNKNOWN
Classifier: Development Status :: 3 - Alpha
Classifier: Intended Audience :: Developers
Classifier: Intended Audience :: Education
Classifier: Natural Language :: English
Classifier: License :: OSI Approved :: Apache Software License
Classifier: Operating System :: OS Independent
Classifier: Programming Language :: Python
Classifier: Programming Language :: Other Scripting Engines
Classifier: Topic :: Games/Entertainment :: Board Games
